__init__.py
nigep/__init__.py
nigep/nigep.py
nigep/nigep_ood.py
nigep/classes/__init__.py
nigep/classes/results_writer.py
nigep/layers/__init__.py
nigep/layers/salt_and_pepper_noise.py
nigep/lib/__init__.py
nigep/lib/apply_noise.py
nigep/lib/consts.py
nigep/lib/folders.py
nigep/lib/functions.py
nigep/lib/metrics.py
nigep/lib/train_model.py
nigep/models/__init__.py
nigep/models/nigep_model.py
nigep-0.1.22.dist-info/LICENSE
nigep-0.1.22.dist-info/METADATA
nigep-0.1.22.dist-info/WHEEL
nigep-0.1.22.dist-info/top_level.txt
nigep-0.1.22.dist-info/RECORD
